agora_rest_client/__init__.py
agora_rest_client/core/__init__.py
agora_rest_client/core/client.py
agora_rest_client/core/domain.py
agora_rest_client/core/errors.py
agora_rest_client/core/exceptions.py
agora_rest_client/core/log.py
agora_rest_client/core/request.py
agora_rest_client/core/response.py
agora_rest_client/services/__init__.py
agora_rest_client/services/cloud_recording/__init__.py
agora_rest_client/services/cloud_recording/v1/__init__.py
agora_rest_client/services/cloud_recording/v1/api.py
agora_rest_client/services/cloud_recording/v1/api_acquire.py
agora_rest_client/services/cloud_recording/v1/api_query.py
agora_rest_client/services/cloud_recording/v1/api_start.py
agora_rest_client/services/cloud_recording/v1/api_stop.py
agora_rest_client/services/cloud_recording/v1/api_update.py
agora_rest_client/services/cloud_recording/v1/api_update_layout.py
agora_rest_client/services/cloud_recording/v1/cloud_recording_client.py
agora_rest_client/services/cloud_recording/v1/errors.py
agora_rest_client/services/cloud_recording/v1/individual_recording/__init__.py
agora_rest_client/services/cloud_recording/v1/individual_recording/api_acquire.py
agora_rest_client/services/cloud_recording/v1/individual_recording/api_query.py
agora_rest_client/services/cloud_recording/v1/individual_recording/api_start.py
agora_rest_client/services/cloud_recording/v1/individual_recording/api_stop.py
agora_rest_client/services/cloud_recording/v1/individual_recording/api_update.py
agora_rest_client/services/cloud_recording/v1/individual_recording/individual_recording_client.py
agora_rest_client/services/cloud_recording/v1/mix_recording/__init__.py
agora_rest_client/services/cloud_recording/v1/mix_recording/api_acquire.py
agora_rest_client/services/cloud_recording/v1/mix_recording/api_query.py
agora_rest_client/services/cloud_recording/v1/mix_recording/api_start.py
agora_rest_client/services/cloud_recording/v1/mix_recording/api_stop.py
agora_rest_client-0.2.0.dist-info/LICENSE
agora_rest_client-0.2.0.dist-info/METADATA
agora_rest_client-0.2.0.dist-info/WHEEL
agora_rest_client-0.2.0.dist-info/top_level.txt
agora_rest_client-0.2.0.dist-info/RECORD
