Metadata-Version: 2.1
Name: agora-rest-client
Version: 0.2.0
Summary: agora rest client
Home-page: https://github.com/AgoraIO-Community/agora-rest-client-python
Author: Agora REST Client
License: Apache LICENSE 2.0
Keywords: agora,rest,client,agora_rest_client,agora-rest-client
Classifier: Development Status :: 5 - Production/Stable
Classifier: Intended Audience :: Developers
Classifier: License :: OSI Approved :: Apache Software License
Classifier: Programming Language :: Python :: 3
Classifier: Topic :: Software Development
Requires-Python: !=3.0.*,!=3.1.*,!=3.2.*
License-File: LICENSE
Requires-Dist: func-timeout >=4.3.5
Requires-Dist: requests >=2.24.0
Requires-Dist: schedule >=1.1.0
